tkla_postgres_client/__init__.py
tkla_postgres_client/builder.py
tkla_postgres_client/core.py
tkla_postgres_client/logger.py
tkla_postgres_client/utils.py
tkla_postgres_client-0.1.0.dist-info/licenses/LICENSE
tkla_postgres_client-0.1.0.dist-info/METADATA
tkla_postgres_client-0.1.0.dist-info/WHEEL
tkla_postgres_client-0.1.0.dist-info/top_level.txt
tkla_postgres_client-0.1.0.dist-info/RECORD
