Metadata-Version: 2.4
Name: tkla_postgres_client
Version: 0.1.0
Summary: Librería simple para interactuar con PostgreSQL usando SQL puro
Home-page: https://github.com/LOVENXON/tkla_postgres_client
Author: Lovenson Pierre
Author-email: lovesonpierre25@gmail.com
License: MIT
Classifier: Programming Language :: Python :: 3
Classifier: License :: OSI Approved :: MIT License
Classifier: Operating System :: OS Independent
Requires-Python: >=3.7
License-File: LICENSE
Dynamic: license-file
